.coveragerc
.mailmap
.pylintrc
.testr.conf
AUTHORS
CONTRIBUTING.rst
ChangeLog
HACKING.rst
LICENSE
MANIFEST.in
README.rst
babel.cfg
openstack-common.conf
requirements.txt
setup.cfg
setup.py
test-requirements.txt
tox.ini
devstack/README.rst
devstack/plugin.sh
devstack/settings
devstack/lib/nec_plugin
doc/source/conf.py
doc/source/contributing.rst
doc/source/devstack.rst
doc/source/index.rst
doc/source/installation.rst
doc/source/readme.rst
doc/source/settings.rst
doc/source/images/nec-openflow-plugin-desgin.png
etc/neutron/plugins/nec/nec.ini
etc/neutron/rootwrap.d/nec-plugin.filters
networking_nec/__init__.py
networking_nec/_i18n.py
networking_nec.egg-info/PKG-INFO
networking_nec.egg-info/SOURCES.txt
networking_nec.egg-info/dependency_links.txt
networking_nec.egg-info/entry_points.txt
networking_nec.egg-info/not-zip-safe
networking_nec.egg-info/pbr.json
networking_nec.egg-info/requires.txt
networking_nec.egg-info/top_level.txt
networking_nec/cmd/__init__.py
networking_nec/cmd/eventlet/__init__.py
networking_nec/cmd/eventlet/plugins/__init__.py
networking_nec/cmd/eventlet/plugins/nec_neutron_agent.py
networking_nec/plugins/__init__.py
networking_nec/plugins/openflow/__init__.py
networking_nec/plugins/openflow/config.py
networking_nec/plugins/openflow/constants.py
networking_nec/plugins/openflow/exceptions.py
networking_nec/plugins/openflow/l2manager.py
networking_nec/plugins/openflow/ofc_client.py
networking_nec/plugins/openflow/ofc_driver_base.py
networking_nec/plugins/openflow/ofc_manager.py
networking_nec/plugins/openflow/packet_filter.py
networking_nec/plugins/openflow/plugin.py
networking_nec/plugins/openflow/portbindings.py
networking_nec/plugins/openflow/router.py
networking_nec/plugins/openflow/router_drivers.py
networking_nec/plugins/openflow/rpc.py
networking_nec/plugins/openflow/utils.py
networking_nec/plugins/openflow/agent/__init__.py
networking_nec/plugins/openflow/agent/l2_agent.py
networking_nec/plugins/openflow/db/__init__.py
networking_nec/plugins/openflow/db/api.py
networking_nec/plugins/openflow/db/models.py
networking_nec/plugins/openflow/db/packetfilter.py
networking_nec/plugins/openflow/db/router.py
networking_nec/plugins/openflow/drivers/__init__.py
networking_nec/plugins/openflow/drivers/pfc.py
